image_classification_helper/__init__.py
image_classification_helper/_nbdev.py
image_classification_helper/core.py
image_classification_helper-0.0.4.dist-info/LICENSE
image_classification_helper-0.0.4.dist-info/METADATA
image_classification_helper-0.0.4.dist-info/WHEEL
image_classification_helper-0.0.4.dist-info/entry_points.txt
image_classification_helper-0.0.4.dist-info/top_level.txt
image_classification_helper-0.0.4.dist-info/RECORD
